Metadata-Version: 2.1
Name: jzou
Version: 0.12.30
Summary: Zou is an API to store and manage the data of your CG production.
Home-page: https://zou.cg-wire.com
Author: CG Wire
Author-email: frank@cg-wire.com
License: GNU Affero General Public License v3
Keywords: cg,asset,shto,api,cg production,asset management
Platform: UNKNOWN
Classifier: Development Status :: 5 - Production/Stable
Classifier: Environment :: Web Environment
Classifier: Framework :: Flask
Classifier: Intended Audience :: Developers
Classifier: Programming Language :: Python :: 3.5
Classifier: Programming Language :: Python :: 3.6
Classifier: Programming Language :: Python :: 3.7
Classifier: Programming Language :: Python :: Implementation :: CPython
Classifier: Programming Language :: Python :: Implementation :: PyPy
Classifier: Topic :: Multimedia :: Graphics
Requires-Dist: flask (==1.1.1)
Requires-Dist: click (==6.7)
Requires-Dist: flask-restful (==0.3.8)
Requires-Dist: flask-fixtures (==0.3.7)
Requires-Dist: flask-sqlalchemy (==2.4.0)
Requires-Dist: flask-bcrypt (==0.7.1)
Requires-Dist: flask-jwt-extended (==3.25.0)
Requires-Dist: flask-migrate (==2.5.2)
Requires-Dist: flask-socketio (==4.1.0)
Requires-Dist: python-engineio (==3.8.2.post1)
Requires-Dist: python-socketio (==4.2.0)
Requires-Dist: flask-principal (==0.4.0)
Requires-Dist: flask-caching (==1.7.1)
Requires-Dist: flask-mail (==0.9.1)
Requires-Dist: flask-fs (==0.6.1)
Requires-Dist: werkzeug (==0.15.5)
Requires-Dist: redis (==3.2.1)
Requires-Dist: ldap3 (==2.8.1)
Requires-Dist: email-validator (==1.0.4)
Requires-Dist: sqlalchemy (==1.3.20)
Requires-Dist: sqlalchemy-utils (==0.34.1)
Requires-Dist: psycopg2-binary (==2.8.6)
Requires-Dist: python-slugify (==3.0.2)
Requires-Dist: boto3
Requires-Dist: pillow (==7.2.0)
Requires-Dist: pytz (==2020.4)
Requires-Dist: babel (==2.7.0)
Requires-Dist: isoweek (==1.3.3)
Requires-Dist: python-swiftclient (==3.8.0)
Requires-Dist: python-keystoneclient (==3.20.0)
Requires-Dist: requests (==2.24.0)
Requires-Dist: ffmpeg-python (==0.2.0)
Requires-Dist: rq (==1.0)
Requires-Dist: six (==1.12.0)
Requires-Dist: gunicorn (==20.0.4)
Requires-Dist: gevent (==20.9.0)
Requires-Dist: gevent-websocket (==0.10.1)
Requires-Dist: slackclient (==1.3.2)
Requires-Dist: gazu (==0.8.8)
Requires-Dist: sh (==1.12.14)
Requires-Dist: pygelf (==0.3.6)
Provides-Extra: dev
Requires-Dist: wheel ; extra == 'dev'
Provides-Extra: prod
Requires-Dist: gunicorn ; extra == 'prod'
Requires-Dist: gevent ; extra == 'prod'
Provides-Extra: test
Requires-Dist: mixer (==5.6.6) ; extra == 'test'
Requires-Dist: pytest (==5.2.0) ; extra == 'test'
Requires-Dist: pytest-cov (==2.7.1) ; extra == 'test'
Requires-Dist: fakeredis ; extra == 'test'
